pyrachy/__init__.py
pyrachy/py.typed
pyrachy/pyrachy.py
pyrachy/loaders/__init__.py
pyrachy/loaders/argv_loader.py
pyrachy/loaders/base_loader.py
pyrachy/loaders/dict_loader.py
pyrachy/loaders/env_loader.py
pyrachy/loaders/file_loader.py
pyrachy-0.1.5.dist-info/METADATA
pyrachy-0.1.5.dist-info/WHEEL
pyrachy-0.1.5.dist-info/licenses/LICENSE.md
pyrachy-0.1.5.dist-info/RECORD
