Metadata-Version: 2.4
Name: pyrachy
Version: 0.1.5
Summary: Add your description here
License-File: LICENSE.md
Requires-Python: >=3.9
Requires-Dist: pyyaml
Requires-Dist: toml
